lloydcoder_nigerian_secrets/__init__.py
lloydcoder_nigerian_secrets/runner.py
lloydcoder_nigerian_secrets-0.1.0.dist-info/METADATA
lloydcoder_nigerian_secrets-0.1.0.dist-info/WHEEL
lloydcoder_nigerian_secrets-0.1.0.dist-info/entry_points.txt
lloydcoder_nigerian_secrets-0.1.0.dist-info/RECORD
