Metadata-Version: 2.4
Name: lloydcoder-nigerian-secrets
Version: 0.1.0
Summary: Detect leaked Nigerian payment keys (Paystack, Flutterwave, etc.)
Project-URL: Homepage, https://github.com/Lloydcoder/nigerian-secret-detectors
Author: Lloydcoder
License: MIT
Requires-Python: >=3.8
